distributed_observability/__init__.py
distributed_observability/core/config.py
distributed_observability/framework/__init__.py
distributed_observability/framework/celery.py
distributed_observability/framework/database.py
distributed_observability/framework/fastapi.py
distributed_observability/framework/grpc.py
distributed_observability/tracing/__init__.py
distributed_observability/tracing/decorators.py
distributed_observability/tracing/tracer.py
distributed_observability/utils/__init__.py
distributed_observability/utils/client.py
distributed_observability_tools-0.1.1.dist-info/METADATA
distributed_observability_tools-0.1.1.dist-info/WHEEL
distributed_observability_tools-0.1.1.dist-info/licenses/LICENSE
distributed_observability_tools-0.1.1.dist-info/RECORD
