Metadata-Version: 2.4
Name: distributed-observability-tools
Version: 0.1.1
Summary: Comprehensive observability tools for distributed systems - tracing, correlation, and metrics
License: MIT
License-File: LICENSE
Keywords: observability,tracing,opentelemetry,distributed-systems,correlation-id,fastapi,microservices
Author: Tushar Khanka
Author-email: tusharkhanka@gmail.com
Requires-Python: >=3.8,<4.0
Classifier: Development Status :: 4 - Beta
Classifier: Intended Audience :: Developers
Classifier: License :: OSI Approved :: MIT License
Classifier: Operating System :: OS Independent
Classifier: Programming Language :: Python :: 3
Classifier: Programming Language :: Python :: 3.8
Classifier: Programming Language :: Python :: 3.9
Classifier: Programming Language :: Python :: 3.10
Classifier: Programming Language :: Python :: 3.11
Classifier: Programming Language :: Python :: 3.12
Classifier: Programming Language :: Python :: 3.13
Classifier: Programming Language :: Python :: 3.14
Classifier: Topic :: Software Development :: Libraries :: Python Modules
Classifier: Topic :: System :: Distributed Computing
Classifier: Topic :: System :: Monitoring
Provides-Extra: all
Provides-Extra: aws
Provides-Extra: celery
Provides-Extra: database
Provides-Extra: fastapi
Provides-Extra: grpc
Provides-Extra: httpx
Requires-Dist: celery (>=5.3.0,<6.0.0) ; extra == "celery" or extra == "all"
Requires-Dist: fastapi (>=0.104.0,<0.105.0) ; extra == "fastapi" or extra == "all"
Requires-Dist: httpx (>=0.25.0,<0.26.0) ; extra == "httpx" or extra == "all"
Requires-Dist: opentelemetry-exporter-otlp-proto-grpc (>=1.21.0,<2.0.0)
Requires-Dist: opentelemetry-instrumentation-botocore (>=0.42b0,<0.43) ; extra == "aws" or extra == "all"
Requires-Dist: opentelemetry-instrumentation-fastapi (>=0.42b0,<0.43) ; extra == "fastapi" or extra == "all"
Requires-Dist: opentelemetry-instrumentation-grpc (>=0.42b0,<0.43) ; extra == "grpc" or extra == "all"
Requires-Dist: opentelemetry-instrumentation-httpx (>=0.42b0,<0.43) ; extra == "httpx" or extra == "all"
Requires-Dist: opentelemetry-instrumentation-redis (>=0.42b0,<0.43) ; extra == "database" or extra == "all"
Requires-Dist: opentelemetry-instrumentation-sqlalchemy (>=0.42b0,<0.43) ; extra == "database" or extra == "all"
Requires-Dist: opentelemetry-sdk (>=1.21.0,<2.0.0)
Project-URL: Bug Reports, https://github.com/tusharkhanka/distributed-observability-tools/issues
Project-URL: Changelog, https://github.com/tusharkhanka/distributed-observability-tools/releases
Project-URL: Documentation, https://github.com/tusharkhanka/distributed-observability-tools#readme
Project-URL: Homepage, https://github.com/tusharkhanka/distributed-observability-tools
Project-URL: Repository, https://github.com/tusharkhanka/distributed-observability-tools
Project-URL: Source, https://github.com/tusharkhanka/distributed-observability-tools
